efficientnet_lite2_pytorch_model/__init__.py
efficientnet_lite2_pytorch_model/models/.gitignore
efficientnet_lite2_pytorch_model/models/efficientnet-lite2-9656183e.pth
efficientnet_lite2_pytorch_model-0.1.0.dist-info/LICENSE
efficientnet_lite2_pytorch_model-0.1.0.dist-info/METADATA
efficientnet_lite2_pytorch_model-0.1.0.dist-info/WHEEL
efficientnet_lite2_pytorch_model-0.1.0.dist-info/top_level.txt
efficientnet_lite2_pytorch_model-0.1.0.dist-info/RECORD
