Metadata-Version: 2.1
Name: efficientnet-lite2-pytorch-model
Version: 0.1.0
Summary: Pretrained Pytorch model file for EfficientNet Lite2
Home-page: https://github.com/ml-illustrated/efficientnet_lite2_pytorch_model
Author: ML Illustrated
Author-email: gerald@ml-illustrated.com
License: UNKNOWN
Platform: UNKNOWN
Classifier: Programming Language :: Python
Classifier: Programming Language :: Python :: 3.6
